opsautopsy/__init__.py
opsautopsy/analyze.py
opsautopsy/cli.py
opsautopsy/config.py
opsautopsy/db.py
opsautopsy/correlator/blast_radius.py
opsautopsy/correlator/incident_builder.py
opsautopsy/correlator/issues.py
opsautopsy/correlator/timeline.py
opsautopsy/output/formatter.py
opsautopsy/output/json_exporter.py
opsautopsy/queries/changes.sql
opsautopsy/queries/events.sql
opsautopsy/queries/workloads.sql
opsautopsy-0.1.0.dist-info/licenses/LICENSE
opsautopsy-0.1.0.dist-info/licenses/NOTICE
opsautopsy-0.1.0.dist-info/METADATA
opsautopsy-0.1.0.dist-info/WHEEL
opsautopsy-0.1.0.dist-info/entry_points.txt
opsautopsy-0.1.0.dist-info/top_level.txt
opsautopsy-0.1.0.dist-info/RECORD
