Metadata-Version: 2.4
Name: opsautopsy
Version: 0.1.0
Summary: Kubernetes post-incident forensics and timeline reconstruction
Author-email: Nikhil V <nikhil.thb@gmail.com>
License-Expression: Apache-2.0
Keywords: kubernetes,devops,sre,incident-response,forensics,observability
Classifier: Development Status :: 3 - Alpha
Classifier: Intended Audience :: Developers
Classifier: Intended Audience :: System Administrators
Classifier: Programming Language :: Python :: 3
Classifier: Programming Language :: Python :: 3.9
Classifier: Programming Language :: Python :: 3.10
Classifier: Programming Language :: Python :: 3.11
Classifier: Programming Language :: Python :: 3.12
Classifier: Operating System :: OS Independent
Classifier: Topic :: System :: Monitoring
Classifier: Topic :: System :: Systems Administration
Requires-Python: >=3.9
License-File: LICENSE
License-File: NOTICE
Requires-Dist: psycopg2-binary>=2.9
Dynamic: license-file
